[
	{
		"inputs": [],
		"payable": false,
		"stateMutability": "nonpayable",
		"type": "constructor"
	},
	{
		"anonymous": false,
		"inputs": [
			{
				"indexed": true,
				"internalType": "address",
				"name": "_first",
				"type": "address"
			},
			{
				"indexed": true,
				"internalType": "address",
				"name": "_second",
				"type": "address"
			},
			{
				"indexed": false,
				"internalType": "uint256",
				"name": "_value",
				"type": "uint256"
			}
		],
		"name": "Splitted",
		"type": "event"
	},
	{
		"anonymous": false,
		"inputs": [
			{
				"indexed": true,
				"internalType": "address",
				"name": "_to",
				"type": "address"
			},
			{
				"indexed": false,
				"internalType": "uint256",
				"name": "_value",
				"type": "uint256"
			}
		],
		"name": "Transfered",
		"type": "event"
	},
	{
		"constant": true,
		"inputs": [
			{
				"internalType": "address",
				"name": "",
				"type": "address"
			}
		],
		"name": "balances",
		"outputs": [
			{
				"internalType": "uint256",
				"name": "",
				"type": "uint256"
			}
		],
		"payable": false,
		"stateMutability": "view",
		"type": "function"
	},
	{
		"constant": false,
		"inputs": [
			{
				"internalType": "address",
				"name": "_first",
				"type": "address"
			},
			{
				"internalType": "address",
				"name": "_second",
				"type": "address"
			}
		],
		"name": "split",
		"outputs": [
			{
				"internalType": "bool",
				"name": "_status",
				"type": "bool"
			}
		],
		"payable": true,
		"stateMutability": "payable",
		"type": "function"
	},
	{
		"constant": false,
		"inputs": [
			{
				"internalType": "uint256",
				"name": "_amount",
				"type": "uint256"
			}
		],
		"name": "withdraw",
		"outputs": [
			{
				"internalType": "bool",
				"name": "_status",
				"type": "bool"
			}
		],
		"payable": false,
		"stateMutability": "nonpayable",
		"type": "function"
	}
]
